{
  "kind": "collectionType",
  "collectionName": "type_rewards",
  "info": {
    "name": "TypeRewards",
    "description": ""
  },
  "options": {
    "increments": true,
    "timestamps": true,
    "draftAndPublish": true
  },
  "pluginOptions": {},
  "attributes": {
    "Title": {
      "type": "string"
    },
    "Description": {
      "type": "richtext"
    },
    "PointNumber": {
      "type": "integer"
    },
    "user_rewards": {
      "via": "type_rewards",
      "collection": "user-rewards"
    }
  }
}
